emarket_data_explorer/__init__.py
emarket_data_explorer/__main__.py
emarket_data_explorer/classtype.py
emarket_data_explorer/cli.py
emarket_data_explorer/config.py
emarket_data_explorer/constant.py
emarket_data_explorer/data_process.py
emarket_data_explorer/database.py
emarket_data_explorer/datatype.py
emarket_data_explorer/shopee_async_crawler.py
emarket_data_explorer/shopee_crawler.py
emarket_data_explorer/shopee_data_explorer.py
emarket_data_explorer/shopee_eda.py
emarket_data_explorer/workflow.py
emarket_data_explorer/tools/__init__.py
emarket_data_explorer/tools/msj.ttf
emarket_data_explorer-1.0.1.dist-info/LICENSE
emarket_data_explorer-1.0.1.dist-info/METADATA
emarket_data_explorer-1.0.1.dist-info/WHEEL
emarket_data_explorer-1.0.1.dist-info/entry_points.txt
emarket_data_explorer-1.0.1.dist-info/top_level.txt
emarket_data_explorer-1.0.1.dist-info/RECORD
