Metadata-Version: 2.1
Name: emarket-data-explorer
Version: 1.0.1
Summary: Read ecommerce data and explore data through Exploratory Data Analysis
Author-email: Paul Yang <paulyang0125@gmail.com>, Kana Kunikata <vinaknkt@gmail.com>
Maintainer: emarket explorer team <paulyang0125@gmail.com>
Maintainer-email: paulyang0125@gmail.com
License: Apache License 2.0
Keywords: ecommerce,data-analysis,reader
Classifier: License :: OSI Approved :: Apache Software License
Classifier: Programming Language :: Python
Classifier: Programming Language :: Python :: 3.8
Classifier: Operating System :: MacOS :: MacOS X
Classifier: Operating System :: Microsoft :: Windows
Requires-Python: >=3.8
License-File: LICENSE
Requires-Dist: typer (>=0.4.1)
Requires-Dist: pandas (>=1.4.3)
Requires-Dist: matplotlib (>=3.5.2)
Requires-Dist: adjustText (>=0.7.3)
Requires-Dist: aiohttp (>=3.8.1)
Requires-Dist: tqdm (>=4.64.0)
Requires-Dist: bs4 (>=0.0.1)
Requires-Dist: lxml (>=4.9.0)
Provides-Extra: dev
Requires-Dist: bumpver ; extra == 'dev'
Requires-Dist: Sphinx ; extra == 'dev'
Requires-Dist: pip-tools ; extra == 'dev'
Requires-Dist: pytest ; extra == 'dev'
